SSIS_Operator/__init__.py
SSIS_Operator/models/SqlQueryParameters.py
SSIS_Operator/models/__init__.py
SSIS_Operator/operators/__init__.py
SSIS_Operator/operators/ssis_package_operator.py
SSIS_Operator/sensors/__init__.py
SSIS_Operator/sensors/ssis_package_sensor.py
airflow_ssis_provider-1.1.1.dist-info/METADATA
airflow_ssis_provider-1.1.1.dist-info/WHEEL
airflow_ssis_provider-1.1.1.dist-info/licenses/LICENSE
airflow_ssis_provider-1.1.1.dist-info/RECORD
