Metadata-Version: 2.4
Name: airflow-ssis-provider
Version: 1.1.1
Summary: A provider package for Apache Airflow to run SSIS Packages
Project-URL: Homepage, https://github.com/gschuurman/airflow-ssis-provider
Project-URL: Issues, https://github.com/gschuurman/airflow-ssis-provider/issues
Author-email: Glenn Schuurman <info@schuurman-it.com>
License-File: LICENSE
Classifier: License :: OSI Approved :: MIT License
Classifier: Programming Language :: Python :: 3
Requires-Python: >=3.10
Requires-Dist: apache-airflow-providers-common-sql>=1.26.0
Requires-Dist: apache-airflow-providers-microsoft-mssql>=4.2.2
Requires-Dist: apache-airflow>=2.10.0
